{"word_list":[{"word":"\u5ead","reading":"\u306b\u308f","meaning":"garden"},{"word":"\u7dd2","reading":"\u3044\u3068\u3050\u3061","meaning":"thread end"},{"word":"\u76bf","reading":"\u3055\u3089","meaning":"plate"},{"word":"\u53e3","reading":"\u304f\u3061","meaning":"mouth"},{"word":"\u4e94","reading":"\u3054","meaning":"five"},{"word":"\u7070","reading":"\u306f\u3044","meaning":"ash"},{"word":"\u5c71","reading":"\u3084\u307e","meaning":"mountain"},{"word":"\u5c4b","reading":"\u3084","meaning":"(something) shop"},{"word":"\u5f37","reading":"\u304d\u3087\u3046","meaning":"a little over"},{"word":"\u9ce5","reading":"\u3068\u308a","meaning":"bird"},{"word":"\u99c5","reading":"\u3048\u304d","meaning":"station"},{"word":"\u4e00","reading":"\u3044\u3061","meaning":"one"},{"word":"\u5bb6","reading":"\u3044\u3048","meaning":"house"},{"word":"\u5bb6\u5ead","reading":"\u304b\u3066\u3044","meaning":"home"},{"word":"\u4e00\u7dd2","reading":"\u3044\u3063\u3057\u3087","meaning":"together"},{"word":"\u4e94\u3064","reading":"\u3044\u3064\u3064","meaning":"five"},{"word":"\u4e00\u5bb6","reading":"\u3044\u3063\u304b","meaning":"a house"},{"word":"\u6691\u3044","reading":"\u3042\u3064\u3044","meaning":"hot (weather, etc.)"},{"word":"\u5f37\u3044","reading":"\u3064\u3088\u3044","meaning":"strong"},{"word":"\u4e94\u5c71","reading":"\u3054\u3055\u3093","meaning":"five most important temples of a region"},{"word":"\u5c71\u9ce5","reading":"\u3084\u307e\u3069\u308a","meaning":"copper pheasant (Phasianus soemmerringii)"},{"word":"\u5c71\u5bb6","reading":"\u3084\u307e\u304c","meaning":"mountain villa"},{"word":"\u9ce5\u5c4b","reading":"\u3068\u3084","meaning":"chicken coop"},{"word":"\u4e00\u3064","reading":"\u3072\u3068\u3064","meaning":"one"},{"word":"\u4e00\u5c71","reading":"\u3044\u3063\u3055\u3093","meaning":"a mountain"},{"word":"\u4e00\u76bf","reading":"\u3072\u3068\u3055\u3089","meaning":"plate"},{"word":"\u5bb6\u5c4b","reading":"\u304b\u304a\u304f","meaning":"house"},{"word":"\u5c71\u5c71","reading":"\u3084\u307e\u3084\u307e","meaning":"(many) mountains"},{"word":"\u7070\u76bf","reading":"\u306f\u3044\u3056\u3089","meaning":"ashtray"},{"word":"\u53e3\u53e3","reading":"\u304f\u3061\u3050\u3061","meaning":"each entrance"},{"word":"\u4e00\u4e00","reading":"\u3044\u3061\u3044\u3061","meaning":"one-by-one"},{"word":"\u5bb6\u5bb6","reading":"\u3044\u3048\u3044\u3048","meaning":"every house or family"},{"word":"\u4e00\u53e3","reading":"\u3072\u3068\u304f\u3061","meaning":"mouthful"},{"word":"\u4e00\u3064\u5bb6","reading":"\u3072\u3068\u3064\u3084","meaning":"one house"},{"word":"\u4e00\u3064\u4e00\u3064","reading":"\u3072\u3068\u3064\u3072\u3068\u3064","meaning":"one-by-one"}],"character_list":["\u53e3","\u5bb6","\u5ead","\u4e00","\u7dd2","\u9ce5","\u5c4b","\u6691","\u3044","\u4e94","\u3064","\u7070","\u76bf","\u99c5","\u5f37","\u5c71"]}
