{"word_list":[{"word":"\u524d","reading":"\u3055\u304d","meaning":"previous"},{"word":"\u672c","reading":"\u3082\u3068","meaning":"origin"},{"word":"\u5e97","reading":"\u307f\u305b","meaning":"store"},{"word":"\u7686","reading":"\u307f\u306a","meaning":"all"},{"word":"\u663c","reading":"\u3072\u308b","meaning":"noon"},{"word":"\u8336","reading":"\u3061\u3083","meaning":"tea"},{"word":"\u4e0b","reading":"\u3057\u305f","meaning":"below"},{"word":"\u68da","reading":"\u305f\u306a","meaning":"shelf"},{"word":"\u5acc","reading":"\u3044\u3084","meaning":"disagreeable"},{"word":"\u6c60","reading":"\u3044\u3051","meaning":"pond"},{"word":"\u5e97\u68da","reading":"\u307f\u305b\u3060\u306a","meaning":"display shelf (in a store)"},{"word":"\u4e0b\u524d","reading":"\u3057\u305f\u307e\u3048","meaning":"part of the fabric that is tucked closest to the skin when wearing a garment that is wrapped in front of one (such as a kimono)"},{"word":"\u6696\u304b","reading":"\u3042\u305f\u305f\u304b","meaning":"warm"},{"word":"\u8336\u68da","reading":"\u3061\u3083\u3060\u306a","meaning":"shelf on which tea and tea implements are kept"},{"word":"\u672c\u672c","reading":"\u3082\u3068\u3082\u3068","meaning":"originally"},{"word":"\u524d\u524d","reading":"\u307e\u3048\u307e\u3048","meaning":"beforehand"},{"word":"\u5acc\u3044","reading":"\u304d\u3089\u3044","meaning":"dislike"},{"word":"\u8336\u8336","reading":"\u3061\u3083\u3061\u3083","meaning":"disruption"},{"word":"\u672c\u68da","reading":"\u307b\u3093\u3060\u306a","meaning":"bookshelves"},{"word":"\u663c\u524d","reading":"\u3072\u308b\u307e\u3048","meaning":"forenoon"},{"word":"\u5acc\u5acc","reading":"\u3044\u3084\u3044\u3084","meaning":"unwillingly"},{"word":"\u6696\u3044","reading":"\u3042\u305f\u305f\u304b\u3044","meaning":"warm"},{"word":"\u55ab\u8336","reading":"\u304d\u3063\u3055","meaning":"tea drinking"},{"word":"\u8336\u5e97","reading":"\u3055\u3066\u3093","meaning":"tea house"},{"word":"\u4e0b\u4e0b","reading":"\u3057\u305f\u3058\u305f","meaning":"the lower classes"},{"word":"\u672c\u5e97","reading":"\u307b\u3093\u3066\u3093","meaning":"head office"},{"word":"\u6696\u304b\u3055","reading":"\u3042\u305f\u305f\u304b\u3055","meaning":"warmth"},{"word":"\u4e0b\u3055\u3044","reading":"\u304f\u3060\u3055\u3044","meaning":"please give me"},{"word":"\u7686\u3055\u3093","reading":"\u307f\u306a\u3055\u3093","meaning":"all"},{"word":"\u6696\u304b\u3044","reading":"\u3042\u305f\u305f\u304b\u3044","meaning":"warm"},{"word":"\u55ab\u8336\u5e97","reading":"\u304d\u3063\u3055\u3066\u3093","meaning":"coffee lounge"}],"character_list":["\u663c","\u672c","\u68da","\u5acc","\u4e0b","\u7686","\u3055","\u3093","\u55ab","\u8336","\u5e97","\u6c60","\u6696","\u304b","\u3044","\u524d"]}
