{"word_list":[{"word":"\u56db","reading":"\u3057","meaning":"four"},{"word":"\u9752","reading":"\u3042\u304a","meaning":"blue"},{"word":"\u4e0a","reading":"\u3046\u3048","meaning":"above"},{"word":"\u4f4f","reading":"\u3058\u3085\u3046","meaning":"dwelling"},{"word":"\u66f2","reading":"\u304d\u3087\u304f","meaning":"tune"},{"word":"\u9580","reading":"\u3068","meaning":"door (esp. Japanese-style)"},{"word":"\u516b","reading":"\u306f\u3061","meaning":"eight"},{"word":"\u7740","reading":"\u3061\u3083\u304f","meaning":"counter for suits of clothing"},{"word":"\u7a7a","reading":"\u304b\u3089","meaning":"emptiness"},{"word":"\u5acc","reading":"\u3044\u3084","meaning":"disagreeable"},{"word":"\u5bd2","reading":"\u304b\u3093","meaning":"midwinter"},{"word":"\u516b\u3064","reading":"\u3084\u3063\u3064","meaning":"eight"},{"word":"\u7a7a\u7a7a","reading":"\u304f\u3046\u304f\u3046","meaning":"empty"},{"word":"\u4e0a\u7740","reading":"\u3046\u308f\u304e","meaning":"coat"},{"word":"\u5acc\u3044","reading":"\u304d\u3089\u3044","meaning":"dislike"},{"word":"\u7740\u308b","reading":"\u304d\u308b","meaning":"to wear (in modern Japanese, from the shoulders down)"},{"word":"\u5bd2\u3044","reading":"\u3055\u3080\u3044","meaning":"cold (e.g. weather)"},{"word":"\u9752\u3044","reading":"\u3042\u304a\u3044","meaning":"blue"},{"word":"\u7740\u7740","reading":"\u3061\u3083\u304f\u3061\u3083\u304f","meaning":"steadily"},{"word":"\u4f4f\u3044","reading":"\u3059\u307e\u3044","meaning":"dwelling"},{"word":"\u66f2\u308b","reading":"\u307e\u304c\u308b","meaning":"to bend"},{"word":"\u4e0a\u4e0a","reading":"\u3058\u3087\u3046\u3058\u3087\u3046","meaning":"the best"},{"word":"\u5bd2\u7a7a","reading":"\u3055\u3080\u305e\u3089","meaning":"cold weather"},{"word":"\u9752\u9752","reading":"\u3042\u304a\u3042\u304a","meaning":"verdant"},{"word":"\u56db\u3064","reading":"\u3088\u3063\u3064","meaning":"four"},{"word":"\u5acc\u5acc","reading":"\u3044\u3084\u3044\u3084","meaning":"unwillingly"},{"word":"\u7740\u304f","reading":"\u3064\u304f","meaning":"to arrive at"},{"word":"\u4f4f\u3080","reading":"\u3059\u3080","meaning":"to live (of humans)"},{"word":"\u4e0a\u308b","reading":"\u3042\u304c\u308b","meaning":"to rise"},{"word":"\u7a7a\u304f","reading":"\u3059\u304f","meaning":"to become less crowded"},{"word":"\u4e0a\u7a7a","reading":"\u3058\u3087\u3046\u304f\u3046","meaning":"sky"},{"word":"\u9752\u7a7a","reading":"\u3042\u304a\u305e\u3089","meaning":"blue sky"},{"word":"\u5bd2\u5bd2","reading":"\u3055\u3080\u3056\u3080","meaning":"wintry"},{"word":"\u4f4f\u7740\u304f","reading":"\u3059\u307f\u3064\u304f","meaning":"to settle (in a place)"}],"character_list":["\u66f2","\u308b","\u5acc","\u3044","\u4e0a","\u7740","\u56db","\u3064","\u9580","\u9752","\u304f","\u5bd2","\u4f4f","\u3080","\u516b","\u7a7a"]}
