{"word_list":[{"word":"\u8449","reading":"\u306f","meaning":"leaf"},{"word":"\u554f","reading":"\u3068\u3044","meaning":"question"},{"word":"\u984c","reading":"\u3060\u3044","meaning":"title"},{"word":"\u751f","reading":"\u304d","meaning":"pure"},{"word":"\u767d","reading":"\u3057\u308d","meaning":"white"},{"word":"\u5074","reading":"\u305d\u3070","meaning":"near"},{"word":"\u8a00","reading":"\u3052\u3093","meaning":"word"},{"word":"\u5c45","reading":"\u304d\u3087","meaning":"residence"},{"word":"\u99c5","reading":"\u3048\u304d","meaning":"station"},{"word":"\u6d17\u3044","reading":"\u3042\u3089\u3044","meaning":"washing"},{"word":"\u751f\u308c","reading":"\u3046\u307e\u308c","meaning":"birth"},{"word":"\u767d\u767d","reading":"\u306f\u304f\u306f\u304f","meaning":"clear"},{"word":"\u5c45\u308b","reading":"\u3044\u308b","meaning":"to be (of animate objects)"},{"word":"\u554f\u3044","reading":"\u3068\u3044","meaning":"question"},{"word":"\u751f\u751f","reading":"\u305b\u3044\u305b\u3044","meaning":"lively"},{"word":"\u8a00\u8a00","reading":"\u3052\u3093\u3052\u3093","meaning":"every word"},{"word":"\u8a00\u8449","reading":"\u3053\u3068\u3070","meaning":"language"},{"word":"\u984c\u8a00","reading":"\u3060\u3044\u3052\u3093","meaning":"prefatory words"},{"word":"\u6d17\u6fef","reading":"\u305b\u3093\u305f\u304f","meaning":"washing"},{"word":"\u554f\u984c","reading":"\u3082\u3093\u3060\u3044","meaning":"problem"},{"word":"\u767d\u3044","reading":"\u3057\u308d\u3044","meaning":"white"},{"word":"\u751f\u308b","reading":"\u306a\u308b","meaning":"to bear fruit"},{"word":"\u64ae\u308b","reading":"\u3068\u308b","meaning":"to take (a photo)"},{"word":"\u751f\u308c\u308b","reading":"\u3046\u307e\u308c\u308b","meaning":"to be born"},{"word":"\u751f\u767d\u3044","reading":"\u306a\u307e\u3058\u308d\u3044","meaning":"pale"},{"word":"\u64ae\u308c\u308b","reading":"\u3068\u308c\u308b","meaning":"to be photographed"},{"word":"\u751f\u307e\u308c","reading":"\u3046\u307e\u308c","meaning":"birth"},{"word":"\u751f\u307e\u308c\u308b","reading":"\u3046\u307e\u308c\u308b","meaning":"to be born"}],"character_list":["\u751f","\u307e","\u308c","\u308b","\u8a00","\u8449","\u99c5","\u554f","\u984c","\u6d17","\u6fef","\u64ae","\u5c45","\u5074","\u767d","\u3044"]}
